{
  "unversionedId": "series/algorithm/2022-12-28-二分归并/readme",
  "id": "series/algorithm/2022-12-28-二分归并/readme",
  "title": "2022-12-28-二分归并",
  "description": "南川题解Leetcode 4. Median of Two Sorted Arrays",
  "source": "@site/my-documents/docs/series/algorithm/2022-12-28-二分归并/readme.md",
  "sourceDirName": "series/algorithm/2022-12-28-二分归并",
  "slug": "/series/algorithm/2022-12-28-二分归并/",
  "permalink": "/docs/series/algorithm/2022-12-28-二分归并/",
  "draft": false,
  "editUrl": "https://github.com/markshawn2020/docusaurus/edit/master/my-documents/docs/series/algorithm/2022-12-28-二分归并/readme.md",
  "tags": [],
  "version": "current",
  "lastUpdatedAt": 1539502055,
  "formattedLastUpdatedAt": "2018年10月14日",
  "frontMatter": {},
  "sidebar": "defaultSidebar",
  "previous": {
    "title": "同构子图问题（哈希+字典）",
    "permalink": "/docs/series/algorithm/2021-02-28-同构子图问题（哈希+字典）"
  },
  "next": {
    "title": "readme_draft",
    "permalink": "/docs/series/algorithm/2022-12-28-二分归并/readme_draft"
  }
}