{
  "permalink": "/blog/2021/12/04/一道“全军覆灭”的数学题",
  "editUrl": "https://github.com/markshawn2020/docusaurus/edit/master/my-documents/blog/2021/12-04-一道“全军覆灭”的数学题.md",
  "source": "@site/my-documents/blog/2021/12-04-一道“全军覆灭”的数学题.md",
  "title": "一道“全军覆灭”的数学题",
  "description": "image-20211204223602555",
  "date": "2021-12-04T00:00:00.000Z",
  "formattedDate": "2021/12/04",
  "tags": [],
  "readingTime": 4.375,
  "hasTruncateMarker": false,
  "authors": [],
  "frontMatter": {},
  "prevItem": {
    "title": "编程 | 记与 Webpack 十二小时的奋战",
    "permalink": "/blog/2021/12/24/dev-webpack"
  },
  "nextItem": {
    "title": "考研数学试题编辑",
    "permalink": "/blog/2021/12/04/考研数学试题编辑"
  }
}